ak47/__about__.py
ak47/__init__.py
ak47/_installer.py
ak47/test.py
pkgs/demo/__init__.py
pkgs/demo/demo.py
plucky_ak47-0.1.0b9.data/scripts/_installer.py
plucky_ak47-0.1.0b9.dist-info/DESCRIPTION.rst
plucky_ak47-0.1.0b9.dist-info/METADATA
plucky_ak47-0.1.0b9.dist-info/RECORD
plucky_ak47-0.1.0b9.dist-info/WHEEL
plucky_ak47-0.1.0b9.dist-info/metadata.json
plucky_ak47-0.1.0b9.dist-info/top_level.txt
